okra/__init__.py
okra/assn2_db.py
okra/assn4.py
okra/batch_utils.py
okra/be_nice.py
okra/bus_factor.py
okra/cli.py
okra/distributed.py
okra/error_handling.py
okra/exceptions.py
okra/github.py
okra/gitlogs.py
okra/logging_utils.py
okra/mgmt_api.py
okra/models.py
okra/populate_db.py
okra/repo_mgmt.py
okra/repository_metrics.py
okra/settings.py
okra/proto/__init__.py
okra/proto/assn1_pb2.py
okra/proto/okra_api_pb2.py
okra-2.2.dist-info/LICENSE
okra-2.2.dist-info/METADATA
okra-2.2.dist-info/WHEEL
okra-2.2.dist-info/entry_points.txt
okra-2.2.dist-info/top_level.txt
okra-2.2.dist-info/RECORD
