Metadata-Version: 2.1
Name: okra
Version: 2.2
Summary: UNKNOWN
Home-page: https://okrahealth.github.io/
Author: Tyler Brown
Author-email: tylers.pile@gmail.com
License: MIT
Project-URL: Bug Tracker, https://github.com/okrahealth/okra/issues
Project-URL: Documentation, https://okrahealth.github.io/okra/
Project-URL: Source Code, https://github.com/okrahealth/okra
Platform: UNKNOWN
Classifier: Development Status :: 3 - Alpha
Classifier: Intended Audience :: Developers
Classifier: License :: OSI Approved :: MIT License
Classifier: Natural Language :: English
Classifier: Operating System :: MacOS :: MacOS X
Classifier: Operating System :: POSIX :: Linux
Classifier: Programming Language :: Python
Classifier: Programming Language :: Python :: 3.7
Requires-Python: ==3.7.*
License-File: LICENSE
Requires-Dist: cython
Requires-Dist: click (==7.0)
Requires-Dist: numpy (==1.21)
Requires-Dist: pandas (==1.0.1)
Requires-Dist: protobuf (==3.19)
Requires-Dist: sqlalchemy (==1.3.13)
